LICENSE
lieops/.ipynb_checkpoints/__init__-checkpoint.py
lieops/.ipynb_checkpoints/_checks-checkpoint.py
lieops/__init__.py
lieops/core/.ipynb_checkpoints/__init__-checkpoint.py
lieops/core/.ipynb_checkpoints/birkhoff-checkpoint.py
lieops/core/.ipynb_checkpoints/dragt-checkpoint.py
lieops/core/.ipynb_checkpoints/forest-checkpoint.py
lieops/core/.ipynb_checkpoints/hadamard-checkpoint.py
lieops/core/.ipynb_checkpoints/lie-checkpoint.py
lieops/core/.ipynb_checkpoints/poly-checkpoint.py
lieops/core/.ipynb_checkpoints/tools-checkpoint.py
lieops/core/__init__.py
lieops/core/birkhoff.py
lieops/core/combine/.ipynb_checkpoints/__init__-checkpoint.py
lieops/core/combine/.ipynb_checkpoints/bch-checkpoint.py
lieops/core/combine/.ipynb_checkpoints/magnus-checkpoint.py
lieops/core/combine/__init__.py
lieops/core/combine/bch.py
lieops/core/combine/bch20.csv
lieops/core/combine/magnus.py
lieops/core/dragt.py
lieops/core/forest.py
lieops/core/generators/.ipynb_checkpoints/__init__-checkpoint.py
lieops/core/generators/.ipynb_checkpoints/genfunc-checkpoint.py
lieops/core/generators/__init__.py
lieops/core/generators/genfunc.py
lieops/core/hadamard.py
lieops/core/lie.py
lieops/core/poly.py
lieops/core/tools.py
lieops/linalg/.ipynb_checkpoints/__init__-checkpoint.py
lieops/linalg/.ipynb_checkpoints/checks-checkpoint.py
lieops/linalg/.ipynb_checkpoints/common-checkpoint.py
lieops/linalg/.ipynb_checkpoints/matrix-checkpoint.py
lieops/linalg/.ipynb_checkpoints/misc-checkpoint.py
lieops/linalg/.ipynb_checkpoints/nf-checkpoint.py
lieops/linalg/__init__.py
lieops/linalg/bch/.ipynb_checkpoints/__init__-checkpoint.py
lieops/linalg/bch/.ipynb_checkpoints/bch_2x2-checkpoint.py
lieops/linalg/bch/__init__.py
lieops/linalg/bch/bch_2x2.py
lieops/linalg/checks.py
lieops/linalg/common.py
lieops/linalg/congruence/.ipynb_checkpoints/common-checkpoint.py
lieops/linalg/congruence/.ipynb_checkpoints/takagi-checkpoint.py
lieops/linalg/congruence/.ipynb_checkpoints/williamson-checkpoint.py
lieops-0.2.3.dist-info/LICENSE
lieops-0.2.3.dist-info/COPYING
lieops-0.2.3.dist-info/WHEEL
lieops-0.2.3.dist-info/METADATA
lieops-0.2.3.dist-info/RECORD
